pysel/__init__.py
pysel/ast.py
pysel/errors.py
pysel/lexer.py
pysel/py.typed
pysel/tokens.py
pysel/vm.py
pysel_lang-0.0.6.dist-info/licenses/LICENSE
pysel_lang-0.0.6.dist-info/WHEEL
pysel_lang-0.0.6.dist-info/METADATA
pysel_lang-0.0.6.dist-info/RECORD
