Metadata-Version: 2.4
Name: pysel-lang
Version: 0.0.6
Summary: A simple but powerful embedded expression language for Python.
Keywords: hikari
Author-email: tandemdude <tandemdude1@gmail.com>
Requires-Python: >=3.8.0,<3.14
Classifier: Development Status :: 3 - Alpha
Classifier: License :: OSI Approved :: MIT License
Classifier: Intended Audience :: Developers
Classifier: Natural Language :: English
Classifier: Programming Language :: Python :: 3.8
Classifier: Programming Language :: Python :: 3.9
Classifier: Programming Language :: Python :: 3.10
Classifier: Programming Language :: Python :: 3.11
Classifier: Programming Language :: Python :: 3.12
Classifier: Programming Language :: Python :: Implementation :: CPython
Classifier: Programming Language :: Python :: 3 :: Only
Classifier: Topic :: Software Development :: Interpreters
Classifier: Topic :: Software Development :: Libraries
Classifier: Topic :: Software Development :: Libraries :: Application Frameworks
Classifier: Topic :: Software Development :: Libraries :: Python Modules
License-File: LICENSE
Requires-Dist: nox==2025.2.9 ; extra == "dev"
Requires-Dist: ruff==0.11.2 ; extra == "dev-format"
Requires-Dist: slotscheck>=0.19.0, <1 ; extra == "dev-slotscheck"
Requires-Dist: pytest==8.3.5 ; extra == "dev-test"
Requires-Dist: mypy==1.15.0 ; extra == "dev-typecheck"
Project-URL: Homepage, https://github.com/tandemdude/pysel
Project-URL: Repository, https://github.com/tandemdude/pysel
Provides-Extra: dev
Provides-Extra: dev-format
Provides-Extra: dev-slotscheck
Provides-Extra: dev-test
Provides-Extra: dev-typecheck
